README.md
setup.cfg
setup.py
megad/__init__.py
megad2.egg-info/PKG-INFO
megad2.egg-info/SOURCES.txt
megad2.egg-info/dependency_links.txt
megad2.egg-info/top_level.txt