Metadata-Version: 1.2
Name: megad2
Version: 0.2
Summary: Simple API for ab-log.ru mega-d
Home-page: UNKNOWN
Author: andrewgermanovich
Author-email: andvikt@gmail.com
License: BSD
Platform: UNKNOWN
Requires-Python: >3.7
